.gitignore
README.rst
setup.cfg
setup.py
wee.py
docs/index.rst
docs/rest.rst
tests/__init__.py
tests/test_prefixdispatch.py
tests/test_rest.py
tests/test_wee_exc.py
tests/scan_test/__init__.py
tests/scan_test/othermodule.py
wee.egg-info/PKG-INFO
wee.egg-info/SOURCES.txt
wee.egg-info/dependency_links.txt
wee.egg-info/entry_points.txt
wee.egg-info/requires.txt
wee.egg-info/top_level.txt
wee.egg-info/zip-safe