Metadata-Version: 1.0
Name: wee
Version: 0.1.1
Summary: like itty but uses webob request, response and exception objects
Home-page: UNKNOWN
Author: whit morriss and matt george
Author-email: whit at nocoast dot us
License: MIT
Keywords: web wsgi
Platform: UNKNOWN
